streamlit_local_storage/__init__.py
streamlit_local_storage/example.py
streamlit_local_storage/frontend/build/asset-manifest.json
streamlit_local_storage/frontend/build/bootstrap.min.css
streamlit_local_storage/frontend/build/bootstrap.min.css.map
streamlit_local_storage/frontend/build/index.html
streamlit_local_storage/frontend/build/static/js/main.ea2b1bc7.js
streamlit_local_storage/frontend/build/static/js/main.ea2b1bc7.js.LICENSE.txt
streamlit_local_storage/frontend/build/static/js/main.ea2b1bc7.js.map
streamlit_local_storage-0.0.25.dist-info/LICENSE
streamlit_local_storage-0.0.25.dist-info/METADATA
streamlit_local_storage-0.0.25.dist-info/WHEEL
streamlit_local_storage-0.0.25.dist-info/top_level.txt
streamlit_local_storage-0.0.25.dist-info/RECORD
